{
	"credit": "Made with Blockbench",
	"texture_size": [32, 32],
	"textures": {
		"1": "tfc:block/icicle",
        "particle": "tfc:block/icicle_tip"

	},
	"elements": [
		{
			"from": [8.00685, 0, 0],
			"to": [8.00685, 16, 16],
			"rotation": {"angle": -45, "axis": "y", "origin": [8.00685, 8, 7.99315]},
			"faces": {
				"north": {"uv": [0, 0, 0, 8], "texture": "#missing"},
				"east": {"uv": [8, 0, 16, 8], "texture": "#1"},
				"south": {"uv": [0, 0, 0, 8], "texture": "#missing"},
				"west": {"uv": [8, 8, 16, 16], "texture": "#1"},
				"up": {"uv": [0, 8, 0, 0], "texture": "#missing"},
				"down": {"uv": [0, 0, 0, 8], "texture": "#missing"}
			}
		},
		{
			"from": [8.00685, 0, 0],
			"to": [8.00685, 16, 16],
			"rotation": {"angle": 45, "axis": "y", "origin": [8.00685, 8, 7.99315]},
			"faces": {
				"north": {"uv": [0, 0, 0, 8], "texture": "#missing"},
				"east": {"uv": [0, 0, 8, 8], "texture": "#1"},
				"south": {"uv": [0, 0, 0, 8], "texture": "#missing"},
				"west": {"uv": [0, 8, 8, 16], "texture": "#1"},
				"up": {"uv": [0, 8, 0, 0], "texture": "#missing"},
				"down": {"uv": [0, 0, 0, 8], "texture": "#missing"}
			}
		}
	]
}